pdom/__init__.py
pdom/cli.py
pdom/core.py
pdom/export.py
pdom/module_info.py
pdom/molecule.py
pdom/data/__init__.py
pdom/data/default_config.json
pdom/data/standard_atomic_weight.json
pdom/data/van_der_waals_radii.json
pdom-1.0.0.dist-info/LICENSE.txt
pdom-1.0.0.dist-info/METADATA
pdom-1.0.0.dist-info/WHEEL
pdom-1.0.0.dist-info/entry_points.txt
pdom-1.0.0.dist-info/top_level.txt
pdom-1.0.0.dist-info/zip-safe
pdom-1.0.0.dist-info/RECORD
