Metadata-Version: 2.1
Name: pdom
Version: 1.0.0
Summary: Simulation toolkit for the Photocatalytic Degradation of Organic Molecules
Home-page: https://pdom.rtfd.io/
Author: Hagen Eckert
Author-email: 
License: MIT
Download-URL: https://github.com/theia-dev/pdom/archive/v1.0.0.zip
Keywords: photocatalysis,modeling
Platform: UNKNOWN
Classifier: Development Status :: 5 - Production/Stable
Classifier: Intended Audience :: Science/Research
Classifier: Topic :: Scientific/Engineering
Classifier: Topic :: Scientific/Engineering :: Chemistry
Classifier: License :: OSI Approved :: MIT License
Classifier: Operating System :: OS Independent
Classifier: Programming Language :: Python :: 3.6
Classifier: Programming Language :: Python :: 3.7
Classifier: Programming Language :: Python :: 3.8
Classifier: Programming Language :: Python :: 3 :: Only
Requires-Python: ~=3.6
Requires-Dist: appdirs
Requires-Dist: numpy
Requires-Dist: scipy
Requires-Dist: matplotlib
Requires-Dist: Pillow
Requires-Dist: PubChemPy
Requires-Dist: scikit-image
